Workbook

Sheet Calendario 52 semanas
A2: Calendario anual de publicaciones para Google Business Profile — CleanWorx Auto Detailing
A3: Carpeta de recursos visuales (Drive): https://drive.google.com/drive/folders/cleanworx-gbp-assets
A4: Fecha | B4: Objetivo | C4: Keyword original | D4: Volumen | E4: Título GBP | F4: Texto listo para publicar (inglés) | G4: Idea de foto o video | H4: Botón | I4: Destino | J4: Revisión antes de publicar | K4: Estado
A5: 46314 | B5: Posicionar la protección cerámica antes del invierno y las heladas de NJ | C5: ceramic coating | D5: 60500 | E5: Prepare Your Paint for Winter with Ceramic Coating | F5: Winter in New Jersey brings corrosive road salt, brine slush, and freezing moisture that eat into unprotected clear coats. A professional System X ceramic coating bonds directly with your vehicle's paint, creating an ultra-slick hydrophobic barrier that prevents harsh road grime from bonding. Protect your vehicle at our 19 E. Henry Street studio in Basking Ridge before the first freeze. | G5: Foto real en primer plano de un vehículo recién tratado con gotas de agua perfectamente esféricas sobre el capó en el taller de CleanWorx. | H5: Learn more | I5: https://www.cleanworxnj.com/ceramic-coating?utm_source=google&utm_medium=organic&utm_campaign=gbp_posts&utm_content=update_ceramic_coating_winter_prep_20261019 | J5: Confirmar disponibilidad de turnos de coating en el taller de 19 E. Henry St. | K5: Borrador
A6: 46321 | B6: Captar conductores que necesitan limpieza profunda interior antes del frío | C6: car interior cleaning | D6: 49500 | E6: Deep Interior Cleaning & Stain Extraction in Basking Ridge | F6: Before cold winter weather keeps your vehicle's windows closed for months, refresh your cabin with professional interior detailing. CleanWorx provides deep carpet extraction, upholstery shampooing, steam cleaning for vents and consoles, and conditioning for high-touch leather. Drop off your car at 19 E. Henry Street or request our self-contained mobile detailing unit. | G6: Foto dividida 50/50 de alfombra manchada frente a la sección limpia tras pasar el extractor de inyección y succión. | H6: Book | I6: https://www.cleanworxnj.com/interior-detailing?utm_source=google&utm_medium=organic&utm_campaign=gbp_posts&utm_content=update_interior_deep_cleaning_20261026 | J6: Verificar que los precios de catálogo Square para interior coincidan con la cotización. | K6: Borrador
A7: 46328 | B7: Explicar beneficios del polarizado cerámico para el resplandor solar otoñal e invernal | C7: window tint installation | D7: 18100 | E7: Precision Window Tint Installation in Basking Ridge, NJ | F7: Low autumn and winter sun angles create dangerous glare across New Jersey highways. CleanWorx offers precision-cut Carbon and Ceramic window film installed inside our clean, dust-controlled Basking Ridge studio. Enjoy reduced eye strain, 99% UV rejection, and enhanced cabin comfort backed by manufacturer warranties up to 10 years. Inquire today. | G7: Foto de un sedán premium recién polarizado en el área de trabajo con luz cenital destacando la nitidez del film. | H7: Learn more | I7: https://www.cleanworxnj.com/window-tinting?utm_source=google&utm_medium=organic&utm_campaign=gbp_posts&utm_content=update_window_tint_installation_20261102 | J7: Recordar las garantías oficiales: 2 años en Carbon film y 10 años en Ceramic film. | K7: Borrador
A8: 46335 | B8: Mostrar la diferencia entre encerar y corregir la pintura con pulido profesional | C8: paint correction | D8: 12100 | E8: Remove Swirl Marks with Precision Machine Paint Correction | F8: Waxes only temporarily fill paint imperfections; true paint correction permanently levels the clear coat through controlled multi-stage polishing. At CleanWorx, we measure paint depth before eliminating swirl marks, wash scratches, and oxidation to restore mirror-like clarity. Standalone services start from $350 at our 19 E. Henry Street shop in Basking Ridge. | G8: Foto o video 50/50 iluminado con luz de inspección Scangrip mostrando la mitad pulida libre de remolinos frente a la mitad rayada. | H8: Book | I8: https://www.cleanworxnj.com/paint-correction?utm_source=google&utm_medium=organic&utm_campaign=gbp_posts&utm_content=update_paint_correction_swirl_removal_20261109 | J8: No prometer eliminación total de rayones que traspasen la capa transparente (clear coat). | K8: Borrador
A9: 46342 | B9: Promover la conveniencia del servicio móvil a domicilio o lugar de trabajo | C9: mobile auto detailing | D9: 33100 | E9: Self-Contained Mobile Auto Detailing Brought to Your Door | F9: Busy week in Somerset or Morris County? CleanWorx brings high-end detailing directly to your home driveway or workplace. Our custom mobile rig carries onboard spot-free deionized water and independent power—requiring zero hookups from your property. Available for detailing and tint appointments throughout Basking Ridge, Bernardsville, Bedminster, and beyond. | G9: Foto de la camioneta móvil de CleanWorx operando en la entrada de una residencia, con el equipo organizado. | H9: Learn more | I9: https://www.cleanworxnj.com/mobile-auto-detailing?utm_source=google&utm_medium=organic&utm_campaign=gbp_posts&utm_content=update_mobile_auto_detailing_van_20261116 | J9: Confirmar la regla de tarifa móvil: $50 en servicios menores a $400; sin costo adicional si es $400 o más. | K9: Borrador
A10: 46349 | B10: Enfatizar la descontaminación exterior antes del despliegue de salmuera invernal | C10: exterior car detailing | D10: 3600 | E10: Exterior Hand Detailing & Paint Decontamination | F10: Abrasive automated brush car washes scratch your finish and leave road films behind. CleanWorx exterior detailing includes a gentle multi-bucket hand wash, chemical iron decontamination, clay bar treatment to lift embedded road grit, and long-lasting paint sealant. Keep your exterior protected against winter road brine in Basking Ridge. | G10: Foto del proceso de descontaminación química mostrando la reacción púrpura (iron remover) en pintura y rines. | H10: Book | I10: https://www.cleanworxnj.com/exterior-detailing?utm_source=google&utm_medium=organic&utm_campaign=gbp_posts&utm_content=update_exterior_detailing_prep_20261123 | J10: No usar la palabra 'car wash' como término de servicio principal; enfatizar detallado profesional a mano. | K10: Borrador
A11: 46356 | B11: Reforzar la ubicación local y la experiencia del equipo en 19 E. Henry St | C11: car detailing shop near me | D11: 301000 | E11: Dedicated Detailing Studio in Basking Ridge, NJ | F11: Looking for an independent detailing shop that treats your car like their own? CleanWorx operates from our dedicated facility at 19 E. Henry Street in downtown Basking Ridge. Founded in 2019, our team—Vito, Melqui, and Hemza—personally manages every service with specialized equipment and climate-controlled bays. Stop by or book your appointment online. | G11: Foto del frente del taller en 19 E. Henry St con el equipo de CleanWorx junto a vehículos de clientes. | H11: Get directions | I11: https://maps.google.com/?q=CleanWorx+Auto+Detailing+19+E+Henry+Street+Basking+Ridge+NJ+07920 | J11: Verificar que la dirección y el pin de Google Maps sean exactamente 19 E. Henry St, Basking Ridge, NJ 07920. | K11: Borrador
A12: 46363 | B12: Promover restauración de faros por seguridad ante los días más oscuros del año | C12: headlight restoration | D12: 33100 | E12: Clear Headlight Restoration for Safer Winter Night Driving | F12: Yellowed, hazy headlights can reduce nighttime visibility by more than 75% on dark New Jersey roadways. CleanWorx offers professional multi-stage wet sanding, compounding, and protective UV sealing to restore crystal clarity to oxidized lenses. Available as a $75 add-on to any detail or as a $125 standalone service at our Basking Ridge shop. | G12: Foto comparativa de faro antes (amarillento y opaco) y después (completamente transparente como nuevo). | H12: Learn more | I12: https://www.cleanworxnj.com/add-ons?utm_source=google&utm_medium=organic&utm_campaign=gbp_posts&utm_content=update_headlight_restoration_winter_20261207 | J12: Mantener los precios aprobados de catálogo: $75 como add-on, $125 como servicio independiente. | K12: Borrador
A13: 46370 | B13: Explicar las opciones de durabilidad de System X Ceramic Coating (1, 3 y 6 años) | C13: car ceramic coating | D13: 49500 | E13: System X Certified Ceramic Coating Packages | F13: Not all paint coatings offer the same durability. As a System X certified installer, CleanWorx offers 1-year, 3-year, and 6-year ceramic coating packages engineered to resist salt spray, road oils, and UV breakdown. Every installation includes rigorous prep and single-stage paint enhancement to ensure maximum bonding and gloss. Schedule your consultation today. | G13: Foto del instalador aplicando el coating con aplicador de microfibra sobre panel preparado en taller iluminado. | H13: Learn more | I13: https://www.cleanworxnj.com/ceramic-coating?utm_source=google&utm_medium=organic&utm_campaign=gbp_posts&utm_content=update_system_x_ceramic_packages_20261214 | J13: Confirmar la certificación System X y recordar no afirmar garantía de fábrica hasta validar condiciones del cliente. | K13: Borrador
A14: 46377 | B14: Captar limpiezas de tapicería y asientos para los viajes navideños y visitas familiares | C14: car carpet cleaning | D14: 22200 | E14: Carpet & Upholstery Deep Cleaning for Holiday Road Trips | F14: Hosting family or traveling for the holidays? Make sure your vehicle's interior is clean, fresh, and welcoming. Our heated extractor penetrates deep into automotive carpet fibers to flush out ground-in dirt, winter moisture, and beverage stains. Drop off your vehicle at 19 E. Henry Street in Basking Ridge for our full interior service. | G14: Foto del tanque de recuperación del extractor mostrando el agua oscura extraída frente a las alfombras limpias. | H14: Book | I14: https://www.cleanworxnj.com/interior-detailing?utm_source=google&utm_medium=organic&utm_campaign=gbp_posts&utm_content=update_holiday_carpet_cleaning_20261221 | J14: Confirmar horarios de atención durante la semana festiva (recordar cerrado los domingos). | K14: Borrador
A15: 46384 | B15: Ofrecer remoción de polarizado viejo, morado o con burbujas | C15: windows tint removal | D15: 6600 | E15: Professional Window Tint Removal in Basking Ridge | F15: Is your old window tint bubbling, peeling, or turning purple? Trying to scrape it yourself risks damaging rear defroster lines and glass surfaces. CleanWorx provides professional steam-assisted tint removal starting at $20 per window at our Basking Ridge studio. Replace failing film with premium heat-rejecting Ceramic tint. | G15: Foto del proceso de desprendimiento de film viejo con vapor sin dañar líneas térmicas de la luneta trasera. | H15: Learn more | I15: https://www.cleanworxnj.com/window-tinting?utm_source=google&utm_medium=organic&utm_campaign=gbp_posts&utm_content=update_window_tint_removal_service_20261228 | J15: Verificar que la tarifa base comience en $20 por ventana según el catálogo oficial de servicios. | K15: Borrador
A16: 46391 | B16: Arrancar el año con un plan de mantenimiento y detallado completo | C16: auto detailing service | D16: 110000 | E16: Start the New Year with a Full Vehicle Detail | F16: Give your daily driver the fresh start it deserves this January. CleanWorx full detailing packages combine comprehensive interior deep cleaning with complete exterior decontamination to eliminate accumulated grit and winter grime. Drop off at our 19 E. Henry Street shop or inquire about our self-contained mobile appointment availability. | G16: Foto panorámica de un vehículo completo recién terminado dentro del taller bajo iluminación profesional. | H16: Book | I16: https://www.cleanworxnj.com/?utm_source=google&utm_medium=organic&utm_campaign=gbp_posts&utm_content=update_new_year_full_detail_20270104 | J16: Probar el enlace al sitio web y confirmar que la información de paquetes esté al día. | K16: Borrador
... A56: 46671 | B56: Cerrar el ciclo anual con un paquete de detallado completo y preparar el vehículo para el invierno | C56: full car detail | D56: 1000 | E56: Annual Vehicle Reset: Complete Full Car Detail | F56: Complete the full seasonal care cycle for your car. A CleanWorx full detail thoroughly restores every surface: deep interior shampoo, leather conditioning, exterior chemical decontamination, wheel cleaning, and long-lasting paint sealant. Experience why drivers across New Jersey trust CleanWorx. Schedule your appointment at 19 E. Henry Street. | G56: Foto final de entrega de un vehículo completamente detallado con el cliente recibiendo las llaves con satisfacción. | H56: Book | I56: https://www.cleanworxnj.com/?utm_source=google&utm_medium=organic&utm_campaign=gbp_posts&utm_content=update_annual_full_car_detail_reset_20271011 | J56: Verificar que la cotización de full detail incluya tanto el interior como el exterior según el catálogo. | K56: Borrador

Sheet Resumen
A1: Resumen del calendario GBP — CleanWorx Auto Detailing
A3: Indicador | B3: Valor | D3: Estado | E3: Cantidad
A4: Total de publicaciones | B4: 52 | D4: Borrador | E4: =COUNTIF('Calendario 52 semanas'!$K$5:$K$56,D4)
A5: Frecuencia | B5: 1 por semana | D5: Listo | E5: =COUNTIF('Calendario 52 semanas'!$K$5:$K$56,D5)
A6: Primera publicación | B6: 46314 | D6: Programado | E6: =COUNTIF('Calendario 52 semanas'!$K$5:$K$56,D6)
A7: Última publicación | B7: 46671 | D7: Publicado | E7: =COUNTIF('Calendario 52 semanas'!$K$5:$K$56,D7)
A8: Estado inicial | B8: Borrador
D10: Reglas operativas para cada publicación — CleanWorx
A11: Categoría | B11: Publicaciones | D11: 1 | E11: Usar una sola keyword principal por publicación sin forzar texto repetitivo.
A12: Protección cerámica (Ceramic Coating) | B12: 7 | D12: 2 | E12: Tratar 'near me' como señal de proximidad: redactar de forma natural integrando Basking Ridge, NJ y condados vecinos (Somerset, Morris, Union).
A13: Corrección de pintura (Paint Correction) | B13: 6 | D13: 3 | E13: Cumplir estrictamente la taxonomía UTM: utm_source=google&utm_medium=organic&utm_campaign=gbp_posts&utm_content={tipo}_{tema}_{aaaammdd}.
A14: Polarizado automotriz (Window Tinting) | B14: 8 | D14: 4 | E14: Priorizar fotos y videos reales de vehículos atendidos en el taller de 19 E. Henry St o en la unidad móvil (sin fotos de stock).
A15: Detallado interior (Interior Detailing) | B15: 8 | D15: 5 | E15: Para servicio móvil, aclarar siempre la tarifa de $50 si el subtotal es menor a $400; sin tarifa adicional si es de $400 o más.
A16: Detallado exterior (Exterior Detailing) | B16: 4 | D16: 6 | E16: No prometer eliminación del 100% de rayones profundos sin evaluar pintura previa, ni hacer reclamos médicos o absolutos en purificación de aire / olores.
A17: Servicio móvil a domicilio (Mobile Detailing) | B17: 5 | D17: 7 | E17: Enlazar siempre a la página canónica del servicio correspondiente en el sitio web; nunca enlazar directamente a URLs externas no verificadas ni a Square sin medición.
A18: Servicios suplementarios (Odor, Engine, Headlights) | B18: 5
A19: Taller, equipo y reputación (Basking Ridge Studio & Trust) | B19: 9
A20: Total | B20: =SUM(B12:B19)

Sheet Keywords Ubersuggest
A1: No | B1: Palabra clave | C1: Volumen | D1: CPC | E1: Dificultad pagada | F1: Dificultad SEO | G1: Cluster | H1: Usos en calendario
A2: 1 | B2: professional headlight restoration | C2: 590 | D2: 1.75 | E2: 100 | F2: 26 | G2: Supplemental Services | H2: =COUNTIF('Calendario 52 semanas'!$C$5:$C$56,B2)
A3: 2 | B3: pet hair removal car | C3: 880 | D3: 0.505 | E3: 100 | F3: 36 | G3: Supplemental Services | H3: =COUNTIF('Calendario 52 semanas'!$C$5:$C$56,B3)
A4: 3 | B4: ceramic coating cost | C4: 3600 | D4: 7.06 | E4: 43 | F4: 12 | G4: Ceramic Coating | H4: =COUNTIF('Calendario 52 semanas'!$C$5:$C$56,B4)
A5: 4 | B5: vehicle detailing | C5: 1900 | D5: 3.25 | E5: 28 | F5: 67 | G5: Auto Detailing General | H5: =COUNTIF('Calendario 52 semanas'!$C$5:$C$56,B5)
A6: 5 | B6: mold removal car interior | C6: 720 | D6: 4.19 | E6: 97 | F6: 20 | G6: Interior Detailing | H6: =COUNTIF('Calendario 52 semanas'!$C$5:$C$56,B6)
A7: 6 | B7: professional window tint near me | C7: 390 | D7: 6.37 | E7: 55 | F7: 16 | G7: Window Tinting | H7: =COUNTIF('Calendario 52 semanas'!$C$5:$C$56,B7)
A8: 7 | B8: smoke smell removal car | C8: 1900 | D8: 0.945 | E8: 100 | F8: 30 | G8: Supplemental Services | H8: =COUNTIF('Calendario 52 semanas'!$C$5:$C$56,B8)
A9: 8 | B9: window tint prices near me | C9: 4400 | D9: 2.62 | E9: 62 | F9: 25 | G9: Window Tinting | H9: =COUNTIF('Calendario 52 semanas'!$C$5:$C$56,B9)
A10: 9 | B10: car polishing | C10: 18100 | D10: 1.255 | E10: 100 | F10: 54 | G10: Paint Correction | H10: =COUNTIF('Calendario 52 semanas'!$C$5:$C$56,B10)
A11: 10 | B11: exterior car detailing | C11: 3600 | D11: 2.25 | E11: 61 | F11: 10 | G11: Exterior Detailing | H11: =COUNTIF('Calendario 52 semanas'!$C$5:$C$56,B11)
A12: 11 | B12: how much does it cost to get windows tinted | C12: 1600 | D12: 4.58 | E12: 51 | F12: 10 | G12: Window Tinting | H12: =COUNTIF('Calendario 52 semanas'!$C$5:$C$56,B12)
A13: 12 | B13: tint car windows near me | C13: 368000 | D13: 5.21 | E13: 75 | F13: 26 | G13: Window Tinting | H13: =COUNTIF('Calendario 52 semanas'!$C$5:$C$56,B13)
... A142: 141 | B142: car windows tint near me | C142: 74000 | D142: 4.585 | E142: 56 | F142: 44 | G142: Window Tinting | H142: =COUNTIF('Calendario 52 semanas'!$C$5:$C$56,B142)
A144: Fuente: keyword research CLEANWORX v2.csv (141 palabras clave optimizadas para CleanWorx Auto Detailing & Ceramic Coating)
